{
  "productos_iniciales": [
    {"nombre": "Arroz Grano Largo", "tipo": "COMIDA", "subtipo": "CADUCABLE", "medida": "K", "cantidad_ideal": 500, "seccion_nombre": "Almacén Seco"},
    {"nombre": "Azúcar Blanca", "tipo": "COMIDA", "subtipo": "NO_CADUCABLE", "medida": "K", "cantidad_ideal": 300, "seccion_nombre": "Almacén Seco"},
    {"nombre": "Harina de Trigo", "tipo": "COMIDA", "subtipo": "NO_CADUCABLE", "medida": "K", "cantidad_ideal": 250, "seccion_nombre": "Almacén Seco"},
    {"nombre": "Sal Refinada", "tipo": "COMIDA", "subtipo": "NO_CADUCABLE", "medida": "K", "cantidad_ideal": 120, "seccion_nombre": "Almacén Seco"},
    {"nombre": "Pimienta Negra Molida", "tipo": "COMIDA", "subtipo": "NO_CADUCABLE", "medida": "K", "cantidad_ideal": 25, "seccion_nombre": "Almacén Seco"},
    {"nombre": "Aceite Vegetal", "tipo": "COMIDA", "subtipo": "NO_CADUCABLE", "medida": "L", "cantidad_ideal": 400, "seccion_nombre": "Almacén Seco"},
    {"nombre": "Aceite de Oliva", "tipo": "COMIDA", "subtipo": "NO_CADUCABLE", "medida": "L", "cantidad_ideal": 150, "seccion_nombre": "Almacén Seco"},
    {"nombre": "Vinagre Blanco", "tipo": "COMIDA", "subtipo": "NO_CADUCABLE", "medida": "L", "cantidad_ideal": 60, "seccion_nombre": "Almacén Seco"},
    {"nombre": "Vinagre Balsámico", "tipo": "COMIDA", "subtipo": "NO_CADUCABLE", "medida": "L", "cantidad_ideal": 40, "seccion_nombre": "Almacén Seco"},
    {"nombre": "Salsa de Soya", "tipo": "COMIDA", "subtipo": "NO_CADUCABLE", "medida": "L", "cantidad_ideal": 80, "seccion_nombre": "Almacén Seco"},
    {"nombre": "Fideos Spaghetti", "tipo": "COMIDA", "subtipo": "NO_CADUCABLE", "medida": "K", "cantidad_ideal": 200, "seccion_nombre": "Almacén Seco"},
    {"nombre": "Fideos Penne", "tipo": "COMIDA", "subtipo": "NO_CADUCABLE", "medida": "K", "cantidad_ideal": 180, "seccion_nombre": "Almacén Seco"},
    {"nombre": "Lentejas Secas", "tipo": "COMIDA", "subtipo": "NO_CADUCABLE", "medida": "K", "cantidad_ideal": 140, "seccion_nombre": "Almacén Seco"},
    {"nombre": "Garbanzos Secos", "tipo": "COMIDA", "subtipo": "NO_CADUCABLE", "medida": "K", "cantidad_ideal": 140, "seccion_nombre": "Almacén Seco"},
    {"nombre": "Frijol Negro Seco", "tipo": "COMIDA", "subtipo": "NO_CADUCABLE", "medida": "K", "cantidad_ideal": 160, "seccion_nombre": "Almacén Seco"},
    {"nombre": "Maíz Palomitas", "tipo": "COMIDA", "subtipo": "NO_CADUCABLE", "medida": "K", "cantidad_ideal": 60, "seccion_nombre": "Almacén Seco"},
    {"nombre": "Miel de Abeja", "tipo": "COMIDA", "subtipo": "NO_CADUCABLE", "medida": "L", "cantidad_ideal": 35, "seccion_nombre": "Almacén Seco"},
    {"nombre": "Jarabe de Arce", "tipo": "COMIDA", "subtipo": "NO_CADUCABLE", "medida": "L", "cantidad_ideal": 25, "seccion_nombre": "Almacén Seco"},
    {"nombre": "Café en Grano", "tipo": "COMIDA", "subtipo": "NO_CADUCABLE", "medida": "K", "cantidad_ideal": 90, "seccion_nombre": "Almacén Seco"},
    {"nombre": "Té Negro", "tipo": "COMIDA", "subtipo": "NO_CADUCABLE", "medida": "U", "cantidad_ideal": 800, "seccion_nombre": "Almacén Seco"},
    {"nombre": "Té Verde", "tipo": "COMIDA", "subtipo": "NO_CADUCABLE", "medida": "U", "cantidad_ideal": 600, "seccion_nombre": "Almacén Seco"},
    {"nombre": "Chocolate en Polvo", "tipo": "COMIDA", "subtipo": "NO_CADUCABLE", "medida": "K", "cantidad_ideal": 70, "seccion_nombre": "Almacén Seco"},
    {"nombre": "Cacao en Polvo", "tipo": "COMIDA", "subtipo": "NO_CADUCABLE", "medida": "K", "cantidad_ideal": 55, "seccion_nombre": "Almacén Seco"},
    {"nombre": "Leche Entera UHT", "tipo": "COMIDA", "subtipo": "REFRIGERADO", "medida": "L", "cantidad_ideal": 500, "seccion_nombre": "Cámara de Refrigeración"},
    {"nombre": "Leche Descremada UHT", "tipo": "COMIDA", "subtipo": "REFRIGERADO", "medida": "L", "cantidad_ideal": 300, "seccion_nombre": "Cámara de Refrigeración"},
    {"nombre": "Yogur Natural", "tipo": "COMIDA", "subtipo": "REFRIGERADO", "medida": "K", "cantidad_ideal": 120, "seccion_nombre": "Cámara de Refrigeración"},
    {"nombre": "Queso Cheddar", "tipo": "COMIDA", "subtipo": "REFRIGERADO", "medida": "K", "cantidad_ideal": 90, "seccion_nombre": "Cámara de Refrigeración"},
    {"nombre": "Queso Mozzarella", "tipo": "COMIDA", "subtipo": "REFRIGERADO", "medida": "K", "cantidad_ideal": 90, "seccion_nombre": "Cámara de Refrigeración"},
    {"nombre": "Jamón Cocido", "tipo": "COMIDA", "subtipo": "REFRIGERADO", "medida": "K", "cantidad_ideal": 80, "seccion_nombre": "Cámara de Refrigeración"},
    {"nombre": "Pechuga de Pavo", "tipo": "COMIDA", "subtipo": "REFRIGERADO", "medida": "K", "cantidad_ideal": 80, "seccion_nombre": "Cámara de Refrigeración"},
    {"nombre": "Mantequilla", "tipo": "COMIDA", "subtipo": "REFRIGERADO", "medida": "K", "cantidad_ideal": 70, "seccion_nombre": "Cámara de Refrigeración"},
    {"nombre": "Margarina", "tipo": "COMIDA", "subtipo": "REFRIGERADO", "medida": "K", "cantidad_ideal": 60, "seccion_nombre": "Cámara de Refrigeración"},
    {"nombre": "Huevos Frescos", "tipo": "COMIDA", "subtipo": "REFRIGERADO", "medida": "U", "cantidad_ideal": 3000, "seccion_nombre": "Cámara de Refrigeración"},
    {"nombre": "Manzana Roja", "tipo": "COMIDA", "subtipo": "CADUCABLE", "medida": "K", "cantidad_ideal": 200, "seccion_nombre": "Cámara de Refrigeración"},
    {"nombre": "Pera", "tipo": "COMIDA", "subtipo": "CADUCABLE", "medida": "K", "cantidad_ideal": 140, "seccion_nombre": "Cámara de Refrigeración"},
    {"nombre": "Naranja", "tipo": "COMIDA", "subtipo": "CADUCABLE", "medida": "K", "cantidad_ideal": 220, "seccion_nombre": "Cámara de Refrigeración"},
    {"nombre": "Limón", "tipo": "COMIDA", "subtipo": "CADUCABLE", "medida": "K", "cantidad_ideal": 120, "seccion_nombre": "Cámara de Refrigeración"},
    {"nombre": "Banana", "tipo": "COMIDA", "subtipo": "CADUCABLE", "medida": "K", "cantidad_ideal": 240, "seccion_nombre": "Cámara de Refrigeración"},
    {"nombre": "Fresa", "tipo": "COMIDA", "subtipo": "CADUCABLE", "medida": "K", "cantidad_ideal": 110, "seccion_nombre": "Cámara de Refrigeración"},
    {"nombre": "Uva", "tipo": "COMIDA", "subtipo": "CADUCABLE", "medida": "K", "cantidad_ideal": 130, "seccion_nombre": "Cámara de Refrigeración"},
    {"nombre": "Lechuga Romana", "tipo": "COMIDA", "subtipo": "CADUCABLE", "medida": "K", "cantidad_ideal": 90, "seccion_nombre": "Cámara de Refrigeración"},
    {"nombre": "Tomate", "tipo": "COMIDA", "subtipo": "CADUCABLE", "medida": "K", "cantidad_ideal": 150, "seccion_nombre": "Cámara de Refrigeración"},
    {"nombre": "Zanahoria", "tipo": "COMIDA", "subtipo": "CADUCABLE", "medida": "K", "cantidad_ideal": 140, "seccion_nombre": "Cámara de Refrigeración"},
    {"nombre": "Brócoli", "tipo": "COMIDA", "subtipo": "CADUCABLE", "medida": "K", "cantidad_ideal": 80, "seccion_nombre": "Cámara de Refrigeración"},
    {"nombre": "Pescado Congelado Blanco", "tipo": "COMIDA", "subtipo": "CONGELACION", "medida": "K", "cantidad_ideal": 300, "seccion_nombre": "Cámara de Congelación"},
    {"nombre": "Filete de Salmón", "tipo": "COMIDA", "subtipo": "CONGELACION", "medida": "K", "cantidad_ideal": 260, "seccion_nombre": "Cámara de Congelación"},
    {"nombre": "Camarón Mediano", "tipo": "COMIDA", "subtipo": "CONGELACION", "medida": "K", "cantidad_ideal": 180, "seccion_nombre": "Cámara de Congelación"},
    {"nombre": "Calamar en Anillas", "tipo": "COMIDA", "subtipo": "CONGELACION", "medida": "K", "cantidad_ideal": 120, "seccion_nombre": "Cámara de Congelación"},
    {"nombre": "Pulpo Troceado", "tipo": "COMIDA", "subtipo": "CONGELACION", "medida": "K", "cantidad_ideal": 90, "seccion_nombre": "Cámara de Congelación"},
    {"nombre": "Carne Res Molida", "tipo": "COMIDA", "subtipo": "CONGELACION", "medida": "K", "cantidad_ideal": 260, "seccion_nombre": "Cámara de Congelación"},
    {"nombre": "Carne Res Bistec", "tipo": "COMIDA", "subtipo": "CONGELACION", "medida": "K", "cantidad_ideal": 240, "seccion_nombre": "Cámara de Congelación"},
    {"nombre": "Pechuga de Pollo", "tipo": "COMIDA", "subtipo": "CONGELACION", "medida": "K", "cantidad_ideal": 300, "seccion_nombre": "Cámara de Congelación"},
    {"nombre": "Alitas de Pollo", "tipo": "COMIDA", "subtipo": "CONGELACION", "medida": "K", "cantidad_ideal": 180, "seccion_nombre": "Cámara de Congelación"},
    {"nombre": "Carne de Cerdo Lomo", "tipo": "COMIDA", "subtipo": "CONGELACION", "medida": "K", "cantidad_ideal": 220, "seccion_nombre": "Cámara de Congelación"},
    {"nombre": "Tocino Congelado", "tipo": "COMIDA", "subtipo": "CONGELACION", "medida": "K", "cantidad_ideal": 140, "seccion_nombre": "Cámara de Congelación"},
    {"nombre": "Helado Vainilla", "tipo": "COMIDA", "subtipo": "CONGELACION", "medida": "K", "cantidad_ideal": 160, "seccion_nombre": "Cámara de Congelación"},
    {"nombre": "Helado Chocolate", "tipo": "COMIDA", "subtipo": "CONGELACION", "medida": "K", "cantidad_ideal": 160, "seccion_nombre": "Cámara de Congelación"},
    {"nombre": "Pan Congelado", "tipo": "COMIDA", "subtipo": "CONGELACION", "medida": "K", "cantidad_ideal": 200, "seccion_nombre": "Cámara de Congelación"},
    {"nombre": "Masa de Pizza", "tipo": "COMIDA", "subtipo": "CONGELACION", "medida": "K", "cantidad_ideal": 130, "seccion_nombre": "Cámara de Congelación"},
    {"nombre": "Hielo en Cubos", "tipo": "COMIDA", "subtipo": "CONGELACION", "medida": "K", "cantidad_ideal": 400, "seccion_nombre": "Cámara de Congelación"},
    {"nombre": "Refresco Cola Lata", "tipo": "COMIDA", "subtipo": "BEBIDA", "medida": "U", "cantidad_ideal": 2000, "seccion_nombre": "Bodega de Bebidas"},
    {"nombre": "Refresco Naranja Lata", "tipo": "COMIDA", "subtipo": "BEBIDA", "medida": "U", "cantidad_ideal": 1500, "seccion_nombre": "Bodega de Bebidas"},
    {"nombre": "Agua Mineral Botella", "tipo": "COMIDA", "subtipo": "BEBIDA", "medida": "U", "cantidad_ideal": 4000, "seccion_nombre": "Bodega de Bebidas"},
    {"nombre": "Agua Sin Gas Botella", "tipo": "COMIDA", "subtipo": "BEBIDA", "medida": "U", "cantidad_ideal": 3000, "seccion_nombre": "Bodega de Bebidas"},
    {"nombre": "Jugo Naranja Botella", "tipo": "COMIDA", "subtipo": "BEBIDA", "medida": "U", "cantidad_ideal": 1200, "seccion_nombre": "Bodega de Bebidas"},
    {"nombre": "Jugo Manzana Botella", "tipo": "COMIDA", "subtipo": "BEBIDA", "medida": "U", "cantidad_ideal": 1000, "seccion_nombre": "Bodega de Bebidas"},
    {"nombre": "Cerveza Rubia Botella", "tipo": "COMIDA", "subtipo": "BEBIDA", "medida": "U", "cantidad_ideal": 2500, "seccion_nombre": "Bodega de Bebidas"},
    {"nombre": "Cerveza Negra Botella", "tipo": "COMIDA", "subtipo": "BEBIDA", "medida": "U", "cantidad_ideal": 800, "seccion_nombre": "Bodega de Bebidas"},
    {"nombre": "Vino Tinto Botella", "tipo": "COMIDA", "subtipo": "LICOR", "medida": "U", "cantidad_ideal": 600, "seccion_nombre": "Almacén de vinos y licores"},
    {"nombre": "Vino Blanco Botella", "tipo": "COMIDA", "subtipo": "LICOR", "medida": "U", "cantidad_ideal": 550, "seccion_nombre": "Almacén de vinos y licores"},
    {"nombre": "Ron Oscuro Botella", "tipo": "COMIDA", "subtipo": "LICOR", "medida": "U", "cantidad_ideal": 300, "seccion_nombre": "Almacén de vinos y licores"},
    {"nombre": "Ron Blanco Botella", "tipo": "COMIDA", "subtipo": "LICOR", "medida": "U", "cantidad_ideal": 300, "seccion_nombre": "Almacén de vinos y licores"},
    {"nombre": "Whisky Botella", "tipo": "COMIDA", "subtipo": "LICOR", "medida": "U", "cantidad_ideal": 280, "seccion_nombre": "Almacén de vinos y licores"},
    {"nombre": "Vodka Botella", "tipo": "COMIDA", "subtipo": "LICOR", "medida": "U", "cantidad_ideal": 260, "seccion_nombre": "Almacén de vinos y licores"},
    {"nombre": "Brandy Botella", "tipo": "COMIDA", "subtipo": "LICOR", "medida": "U", "cantidad_ideal": 180, "seccion_nombre": "Almacén de vinos y licores"},
    {"nombre": "Tequila Botella", "tipo": "COMIDA", "subtipo": "LICOR", "medida": "U", "cantidad_ideal": 200, "seccion_nombre": "Almacén de vinos y licores"},
    {"nombre": "Gin Botella", "tipo": "COMIDA", "subtipo": "LICOR", "medida": "U", "cantidad_ideal": 200, "seccion_nombre": "Almacén de vinos y licores"},
    {"nombre": "Desinfectante Superficies", "tipo": "BIENES", "subtipo": "LIMPIEZA", "medida": "L", "cantidad_ideal": 120, "seccion_nombre": "Almacenes de Seguridad"},
    {"nombre": "Detergente Industrial", "tipo": "BIENES", "subtipo": "LIMPIEZA", "medida": "K", "cantidad_ideal": 140, "seccion_nombre": "Almacenes de Seguridad"},
    {"nombre": "Guantes Nitrilo Caja", "tipo": "BIENES", "subtipo": "MEDICOS", "medida": "U", "cantidad_ideal": 2000, "seccion_nombre": "Equipamiento de Emergencia"},
    {"nombre": "Mascarillas Quirúrgicas Caja", "tipo": "BIENES", "subtipo": "MEDICOS", "medida": "U", "cantidad_ideal": 3000, "seccion_nombre": "Equipamiento de Emergencia"},
    {"nombre": "Vendas Elásticas", "tipo": "BIENES", "subtipo": "MEDICOS", "medida": "U", "cantidad_ideal": 500, "seccion_nombre": "Equipamiento de Emergencia"},
    {"nombre": "Alcohol 70%", "tipo": "BIENES", "subtipo": "MEDICOS", "medida": "L", "cantidad_ideal": 120, "seccion_nombre": "Equipamiento de Emergencia"},
    {"nombre": "Linterna LED Industrial", "tipo": "BIENES", "subtipo": "ACTIVOS", "medida": "U", "cantidad_ideal": 60, "seccion_nombre": "Almacén de Repuestos y Mantenimiento"},
    {"nombre": "Batería Recargable Portátil", "tipo": "BIENES", "subtipo": "ACTIVOS", "medida": "U", "cantidad_ideal": 80, "seccion_nombre": "Almacén de Repuestos y Mantenimiento"},
    {"nombre": "Herramienta Multímetro", "tipo": "BIENES", "subtipo": "REPUESTOS", "medida": "U", "cantidad_ideal": 40, "seccion_nombre": "Almacén de Repuestos y Mantenimiento"},
    {"nombre": "Cable Eléctrico Rollo", "tipo": "BIENES", "subtipo": "REPUESTOS", "medida": "M", "cantidad_ideal": 800, "seccion_nombre": "Almacén de Repuestos y Mantenimiento"},
    {"nombre": "Filtro Aire Motor", "tipo": "BIENES", "subtipo": "REPUESTOS", "medida": "U", "cantidad_ideal": 70, "seccion_nombre": "Almacén de Repuestos y Mantenimiento"},
    {"nombre": "Bomba de Agua Reserva", "tipo": "BIENES", "subtipo": "REPUESTOS", "medida": "U", "cantidad_ideal": 20, "seccion_nombre": "Almacén de Repuestos y Mantenimiento"},
    {"nombre": "Lubricante Industrial", "tipo": "BIENES", "subtipo": "REPUESTOS", "medida": "L", "cantidad_ideal": 150, "seccion_nombre": "Almacén de Repuestos y Mantenimiento"},
    {"nombre": "Tornillería Variada Caja", "tipo": "BIENES", "subtipo": "REPUESTOS", "medida": "U", "cantidad_ideal": 500, "seccion_nombre": "Almacén de Repuestos y Mantenimiento"},
    {"nombre": "Pintura Anticorrosiva", "tipo": "BIENES", "subtipo": "REPUESTOS", "medida": "L", "cantidad_ideal": 90, "seccion_nombre": "Almacén de Repuestos y Mantenimiento"},
    {"nombre": "Cepillo Limpieza Industrial", "tipo": "BIENES", "subtipo": "LIMPIEZA", "medida": "U", "cantidad_ideal": 120, "seccion_nombre": "Almacenes de Seguridad"},
    {"nombre": "Paños Microfibra", "tipo": "BIENES", "subtipo": "LIMPIEZA", "medida": "U", "cantidad_ideal": 600, "seccion_nombre": "Almacenes de Seguridad"},
    {"nombre": "Detergente Lavavajillas", "tipo": "BIENES", "subtipo": "LIMPIEZA", "medida": "L", "cantidad_ideal": 200, "seccion_nombre": "Almacenes de Seguridad"},
    {"nombre": "Trapeadores Industriales", "tipo": "BIENES", "subtipo": "LIMPIEZA", "medida": "U", "cantidad_ideal": 100, "seccion_nombre": "Almacenes de Seguridad"},
    {"nombre": "Escobas Industriales", "tipo": "BIENES", "subtipo": "LIMPIEZA", "medida": "U", "cantidad_ideal": 110, "seccion_nombre": "Almacenes de Seguridad"},
    {"nombre": "Desengrasante Potente", "tipo": "BIENES", "subtipo": "LIMPIEZA", "medida": "L", "cantidad_ideal": 140, "seccion_nombre": "Almacenes de Seguridad"},
    {"nombre": "Gel Antibacterial", "tipo": "BIENES", "subtipo": "MEDICOS", "medida": "L", "cantidad_ideal": 160, "seccion_nombre": "Equipamiento de Emergencia"},
    {"nombre": "Kit Primeros Auxilios", "tipo": "BIENES", "subtipo": "MEDICOS", "medida": "U", "cantidad_ideal": 40, "seccion_nombre": "Equipamiento de Emergencia"}
  ]
}
